MANIFEST.in
README.md
requirements.txt
setup.py
herzog/__init__.py
herzog/parser.py
herzog/version.py
herzog.egg-info/PKG-INFO
herzog.egg-info/SOURCES.txt
herzog.egg-info/dependency_links.txt
herzog.egg-info/not-zip-safe
herzog.egg-info/top_level.txt
herzog/data/python_3_boiler.json
scripts/herzog