Metadata-Version: 2.1
Name: herzog
Version: 0.1.0
Summary: Generate Jupyter notebooks.
Home-page: https://github.com/xbrianh/herzog.git
Author: Brian Hannafious
Author-email: bhannafi@ucsc.edu
License: MIT
Platform: MacOS X
Platform: Posix
Classifier: Intended Audience :: Science/Research
Classifier: License :: OSI Approved :: MIT License
Classifier: Programming Language :: Python :: 3.7
